Metadata-Version: 2.1
Name: odoo11-addon-remote-report-to-printer
Version: 11.0.2.1.1
Summary: Report to printer on remotes
Home-page: http://www.agilebg.com
Author: Creu Blanca, Odoo Community Association (OCA)
Author-email: support@odoo-community.org
License: AGPL-3
Platform: UNKNOWN
Classifier: Programming Language :: Python
Classifier: Framework :: Odoo
Classifier: License :: OSI Approved :: GNU Affero General Public License v3
Requires-Python: >=2.7, !=3.0.*, !=3.1.*, !=3.2.*, !=3.3.*, !=3.4.*
Requires-Dist: odoo11-addon-base-remote
Requires-Dist: odoo11-addon-base-report-to-printer
Requires-Dist: odoo (<11.1dev,>=11.0a)
